propius/__init__.py
propius/basic.py
propius/model.py
propius/settings.py
propius/utils.py
propius-0.1.2.dist-info/LICENSE.txt
propius-0.1.2.dist-info/METADATA
propius-0.1.2.dist-info/WHEEL
propius-0.1.2.dist-info/top_level.txt
propius-0.1.2.dist-info/RECORD
